[{"id":"ff808081548816b40154c96e4bdd2342","managementIP":"172.17.2.178","managementIPStatic":false,"serviceTag":"BCQPTS1","health":"GREEN","model":"MXL 10/40Gbe","slot":1,"location":"A1","supported":false},{"id":"ff808081548816b40154c96e4bdd2345","managementIP":"172.17.2.194","managementIPStatic":false,"serviceTag":"GSCXTS1","health":"GREEN","model":"MXL 10/40Gbe","slot":2,"location":"A2","supported":false},{"id":"ff808081548816b40154c96e4bdd2343","managementIP":"172.17.2.223","managementIPStatic":false,"serviceTag":"GFQQTS1","health":"GREEN","model":"PowerEdge M I/O Aggregator","slot":3,"location":"B1","supported":true},{"id":"ff808081548816b40154c96e4bdd2344","managementIP":"172.17.2.190","managementIPStatic":false,"serviceTag":"9BQQTS1","health":"GREEN","model":"PowerEdge M I/O Aggregator","slot":4,"location":"B2","supported":true}]
